<doi_batch xmlns="http://www.crossref.org/schema/4.3.7" xmlns:xsi="http://www.w3.org/2001/XMLSchema-instance" xsi:schemaLocation="http://www.crossref.org/schema/4.3.7 http://www.crossref.org/schemas/crossref4.3.7.xsd" version="4.3.7">
	<head>
		<doi_batch_id>blizzard_2023</doi_batch_id>
		<timestamp>1705397838043004</timestamp>
		<depositor>
			<depositor_name>Martin Cooke</depositor_name> 
			<email_address>m.cooke@ikerbasque.org</email_address>
		</depositor>
		<registrant>International Speech Communication Association</registrant> 
	</head>
	<body>
		<conference>
			<event_metadata>
				<conference_name>18th Blizzard Challenge Workshop</conference_name>
				<conference_acronym>blizzard_2023</conference_acronym>
				<conference_date>29 August 2023</conference_date>
			</event_metadata>
			<proceedings_metadata language="en">
				<proceedings_title>18th Blizzard Challenge Workshop</proceedings_title>
				<publisher>
					<publisher_name>ISCA</publisher_name>
					<publisher_place>ISCA</publisher_place>
				</publisher>
				<publication_date>
					<year>2023</year>
				</publication_date>
				<noisbn reason='simple_series'/>
				<doi_data>
					<doi>10.21437/Blizzard.2023</doi>
					<timestamp>1705397838043004</timestamp>
					<resource>https://www.isca-archive.org/blizzard_2023/</resource>
				</doi_data>
			</proceedings_metadata>
				<conference_paper publication_type="full_text">
					<contributors>
						<person_name sequence="first" contributor_role="author">
<given_name>Tiberiu</given_name>
<surname>Boros</surname>
</person_name><person_name sequence="additional" contributor_role="author">
<given_name>Stefan Daniel</given_name>
<surname>Dumitrescu</surname>
</person_name><person_name sequence="additional" contributor_role="author">
<given_name>Ionut</given_name>
<surname>Mironica</surname>
</person_name><person_name sequence="additional" contributor_role="author">
<given_name>Radu</given_name>
<surname>Chivereanu</surname>
</person_name>
					</contributors>
					<titles><title>Generative Adversarial Training for Text-to-Speech Synthesis Based on Raw Phonetic Input and Explicit Prosody Modelling</title></titles>
					<publication_date media_type='online'>
						<month>8</month>
						<day>29</day>
						<year>2023</year>
					</publication_date>
					<pages>
						<first_page>69</first_page>
						<last_page>74</last_page>
					</pages>
					<doi_data>
						<doi>10.21437/Blizzard.2023-9</doi>
						<resource>https://www.isca-archive.org/blizzard_2023/boros23_blizzard.html</resource>
					</doi_data>
				</conference_paper>
				<conference_paper publication_type="full_text">
					<contributors>
						<person_name sequence="first" contributor_role="author">
<given_name>Yaohua</given_name>
<surname>Bu</surname>
</person_name><person_name sequence="additional" contributor_role="author">
<given_name>Yang</given_name>
<surname>Zhao</surname>
</person_name>
					</contributors>
					<titles><title>Xpress: The 10AI Speech Synthesis System for Blizzard Challenge 2023</title></titles>
					<publication_date media_type='online'>
						<month>8</month>
						<day>29</day>
						<year>2023</year>
					</publication_date>
					<pages>
						<first_page>119</first_page>
						<last_page>123</last_page>
					</pages>
					<doi_data>
						<doi>10.21437/Blizzard.2023-18</doi>
						<resource>https://www.isca-archive.org/blizzard_2023/bu23_blizzard.html</resource>
					</doi_data>
				</conference_paper>
				<conference_paper publication_type="full_text">
					<contributors>
						<person_name sequence="first" contributor_role="author">
<given_name>Haolin</given_name>
<surname>Chen</surname>
</person_name><person_name sequence="additional" contributor_role="author">
<given_name>Mutian</given_name>
<surname>He</surname>
</person_name><person_name sequence="additional" contributor_role="author">
<given_name>Louise Coppieters de</given_name>
<surname>Gibson</surname>
</person_name><person_name sequence="additional" contributor_role="author">
<given_name>Philip N.</given_name>
<surname>Garner</surname>
</person_name>
					</contributors>
					<titles><title>The Idiap Speech Synthesis System for the Blizzard Challenge 2023</title></titles>
					<publication_date media_type='online'>
						<month>8</month>
						<day>29</day>
						<year>2023</year>
					</publication_date>
					<pages>
						<first_page>93</first_page>
						<last_page>97</last_page>
					</pages>
					<doi_data>
						<doi>10.21437/Blizzard.2023-13</doi>
						<resource>https://www.isca-archive.org/blizzard_2023/chen23_blizzard.html</resource>
					</doi_data>
				</conference_paper>
				<conference_paper publication_type="full_text">
					<contributors>
						<person_name sequence="first" contributor_role="author">
<given_name>Yuepeng</given_name>
<surname>Jiang</surname>
</person_name><person_name sequence="additional" contributor_role="author">
<given_name>Kun</given_name>
<surname>Song</surname>
</person_name><person_name sequence="additional" contributor_role="author">
<given_name>Fengyu</given_name>
<surname>Yang</surname>
</person_name><person_name sequence="additional" contributor_role="author">
<given_name>Lei</given_name>
<surname>Xie</surname>
</person_name><person_name sequence="additional" contributor_role="author">
<given_name>Meng</given_name>
<surname>Meng</surname>
</person_name><person_name sequence="additional" contributor_role="author">
<given_name>Yu</given_name>
<surname>Ji</surname>
</person_name><person_name sequence="additional" contributor_role="author">
<given_name>Yujun</given_name>
<surname>Wang</surname>
</person_name>
					</contributors>
					<titles><title>The Xiaomi-ASLP Text-to-speech System for Blizzard Challenge 2023</title></titles>
					<publication_date media_type='online'>
						<month>8</month>
						<day>29</day>
						<year>2023</year>
					</publication_date>
					<pages>
						<first_page>109</first_page>
						<last_page>113</last_page>
					</pages>
					<doi_data>
						<doi>10.21437/Blizzard.2023-16</doi>
						<resource>https://www.isca-archive.org/blizzard_2023/jiang23_blizzard.html</resource>
					</doi_data>
				</conference_paper>
				<conference_paper publication_type="full_text">
					<contributors>
						<person_name sequence="first" contributor_role="author">
<given_name>Martin</given_name>
<surname>Lenglet</surname>
</person_name><person_name sequence="additional" contributor_role="author">
<given_name>Olivier</given_name>
<surname>Perrotin</surname>
</person_name><person_name sequence="additional" contributor_role="author">
<given_name>Gérard</given_name>
<surname>Bailly</surname>
</person_name>
					</contributors>
					<titles><title>The GIPSA-Lab Text-To-Speech System for the Blizzard Challenge 2023</title></titles>
					<publication_date media_type='online'>
						<month>8</month>
						<day>29</day>
						<year>2023</year>
					</publication_date>
					<pages>
						<first_page>34</first_page>
						<last_page>39</last_page>
					</pages>
					<doi_data>
						<doi>10.21437/Blizzard.2023-3</doi>
						<resource>https://www.isca-archive.org/blizzard_2023/lenglet23_blizzard.html</resource>
					</doi_data>
				</conference_paper>
				<conference_paper publication_type="full_text">
					<contributors>
						<person_name sequence="first" contributor_role="author">
<given_name>Chunhui</given_name>
<surname>Lu</surname>
</person_name><person_name sequence="additional" contributor_role="author">
<given_name>Jeasung</given_name>
<surname>Lee</surname>
</person_name><person_name sequence="additional" contributor_role="author">
<given_name>Xue</given_name>
<surname>Wen</surname>
</person_name><person_name sequence="additional" contributor_role="author">
<given_name>Xiaoyan</given_name>
<surname>Lou</surname>
</person_name><person_name sequence="additional" contributor_role="author">
<given_name>Junkwang</given_name>
<surname>Oh</surname>
</person_name>
					</contributors>
					<titles><title>The Samsung Speech Synthesis System for Blizzard Challenge 2023</title></titles>
					<publication_date media_type='online'>
						<month>8</month>
						<day>29</day>
						<year>2023</year>
					</publication_date>
					<pages>
						<first_page>52</first_page>
						<last_page>57</last_page>
					</pages>
					<doi_data>
						<doi>10.21437/Blizzard.2023-6</doi>
						<resource>https://www.isca-archive.org/blizzard_2023/lu23_blizzard.html</resource>
					</doi_data>
				</conference_paper>
				<conference_paper publication_type="full_text">
					<contributors>
						<person_name sequence="first" contributor_role="author">
<given_name>Yi</given_name>
<surname>Lu</surname>
</person_name><person_name sequence="additional" contributor_role="author">
<given_name>Ruibo</given_name>
<surname>Fu</surname>
</person_name><person_name sequence="additional" contributor_role="author">
<given_name>Xin</given_name>
<surname>Qi</surname>
</person_name><person_name sequence="additional" contributor_role="author">
<given_name>Zhengqi</given_name>
<surname>Wen</surname>
</person_name><person_name sequence="additional" contributor_role="author">
<given_name>Jianhua</given_name>
<surname>Tao</surname>
</person_name><person_name sequence="additional" contributor_role="author">
<given_name>Jiangyan</given_name>
<surname>Yi</surname>
</person_name><person_name sequence="additional" contributor_role="author">
<given_name>Tao</given_name>
<surname>Wang</surname>
</person_name><person_name sequence="additional" contributor_role="author">
<given_name>Yong</given_name>
<surname>Ren</surname>
</person_name><person_name sequence="additional" contributor_role="author">
<given_name>Chuyuan</given_name>
<surname>Zhang</surname>
</person_name><person_name sequence="additional" contributor_role="author">
<given_name>Chenyu</given_name>
<surname>Yang</surname>
</person_name><person_name sequence="additional" contributor_role="author">
<given_name>Wenling</given_name>
<surname>Shi</surname>
</person_name>
					</contributors>
					<titles><title>The VIBVG Speech Synthesis System for Blizzard Challenge 2023</title></titles>
					<publication_date media_type='online'>
						<month>8</month>
						<day>29</day>
						<year>2023</year>
					</publication_date>
					<pages>
						<first_page>103</first_page>
						<last_page>108</last_page>
					</pages>
					<doi_data>
						<doi>10.21437/Blizzard.2023-15</doi>
						<resource>https://www.isca-archive.org/blizzard_2023/lu23b_blizzard.html</resource>
					</doi_data>
				</conference_paper>
				<conference_paper publication_type="full_text">
					<contributors>
						<person_name sequence="first" contributor_role="author">
<given_name>Florian</given_name>
<surname>Lux</surname>
</person_name><person_name sequence="additional" contributor_role="author">
<given_name>Julia</given_name>
<surname>Koch</surname>
</person_name><person_name sequence="additional" contributor_role="author">
<given_name>Sarina</given_name>
<surname>Meyer</surname>
</person_name><person_name sequence="additional" contributor_role="author">
<given_name>Thomas</given_name>
<surname>Bott</surname>
</person_name><person_name sequence="additional" contributor_role="author">
<given_name>Nadja</given_name>
<surname>Schauffler</surname>
</person_name><person_name sequence="additional" contributor_role="author">
<given_name>Pavel</given_name>
<surname>Denisov</surname>
</person_name><person_name sequence="additional" contributor_role="author">
<given_name>Antje</given_name>
<surname>Schweitzer</surname>
</person_name><person_name sequence="additional" contributor_role="author">
<given_name>Ngoc Thang</given_name>
<surname>Vu</surname>
</person_name>
					</contributors>
					<titles><title>The IMS Toucan System for the Blizzard Challenge 2023</title></titles>
					<publication_date media_type='online'>
						<month>8</month>
						<day>29</day>
						<year>2023</year>
					</publication_date>
					<pages>
						<first_page>40</first_page>
						<last_page>45</last_page>
					</pages>
					<doi_data>
						<doi>10.21437/Blizzard.2023-4</doi>
						<resource>https://www.isca-archive.org/blizzard_2023/lux23_blizzard.html</resource>
					</doi_data>
				</conference_paper>
				<conference_paper publication_type="full_text">
					<contributors>
						<person_name sequence="first" contributor_role="author">
<given_name>Qiaowei</given_name>
<surname>Ma</surname>
</person_name><person_name sequence="additional" contributor_role="author">
<given_name>Weiheng</given_name>
<surname>Liu</surname>
</person_name><person_name sequence="additional" contributor_role="author">
<given_name>Yitao</given_name>
<surname>Yang</surname>
</person_name><person_name sequence="additional" contributor_role="author">
<given_name>Chao</given_name>
<surname>Xu</surname>
</person_name><person_name sequence="additional" contributor_role="author">
<given_name>Hongtao</given_name>
<surname>Ling</surname>
</person_name><person_name sequence="additional" contributor_role="author">
<given_name>Jinghui</given_name>
<surname>Zhong</surname>
</person_name>
					</contributors>
					<titles><title>The SCUT Text-To-Speech System for the Blizzard Challenge 2023</title></titles>
					<publication_date media_type='online'>
						<month>8</month>
						<day>29</day>
						<year>2023</year>
					</publication_date>
					<pages>
						<first_page>58</first_page>
						<last_page>62</last_page>
					</pages>
					<doi_data>
						<doi>10.21437/Blizzard.2023-7</doi>
						<resource>https://www.isca-archive.org/blizzard_2023/ma23_blizzard.html</resource>
					</doi_data>
				</conference_paper>
				<conference_paper publication_type="full_text">
					<contributors>
						<person_name sequence="first" contributor_role="author">
<given_name>Olivier</given_name>
<surname>Perrotin</surname>
</person_name><person_name sequence="additional" contributor_role="author">
<given_name>Brooke</given_name>
<surname>Stephenson</surname>
</person_name><person_name sequence="additional" contributor_role="author">
<given_name>Silvain</given_name>
<surname>Gerber</surname>
</person_name><person_name sequence="additional" contributor_role="author">
<given_name>Gérard</given_name>
<surname>Bailly</surname>
</person_name>
					</contributors>
					<titles><title>The Blizzard Challenge 2023</title></titles>
					<publication_date media_type='online'>
						<month>8</month>
						<day>29</day>
						<year>2023</year>
					</publication_date>
					<pages>
						<first_page>1</first_page>
						<last_page>27</last_page>
					</pages>
					<doi_data>
						<doi>10.21437/Blizzard.2023-1</doi>
						<resource>https://www.isca-archive.org/blizzard_2023/perrotin23_blizzard.html</resource>
					</doi_data>
				</conference_paper>
				<conference_paper publication_type="full_text">
					<contributors>
						<person_name sequence="first" contributor_role="author">
<given_name>Xin</given_name>
<surname>Qi</surname>
</person_name><person_name sequence="additional" contributor_role="author">
<given_name>Xiaopeng</given_name>
<surname>Wang</surname>
</person_name><person_name sequence="additional" contributor_role="author">
<given_name>Zhiyong</given_name>
<surname>Wang</surname>
</person_name><person_name sequence="additional" contributor_role="author">
<given_name>Wang</given_name>
<surname>Liu</surname>
</person_name><person_name sequence="additional" contributor_role="author">
<given_name>Mingming</given_name>
<surname>Ding</surname>
</person_name><person_name sequence="additional" contributor_role="author">
<given_name>-</given_name>
<surname>ShuchenShi</surname>
</person_name>
					</contributors>
					<titles><title>The FruitShell French synthesis system at the Blizzard 2023 Challenge</title></titles>
					<publication_date media_type='online'>
						<month>8</month>
						<day>29</day>
						<year>2023</year>
					</publication_date>
					<pages>
						<first_page>114</first_page>
						<last_page>118</last_page>
					</pages>
					<doi_data>
						<doi>10.21437/Blizzard.2023-17</doi>
						<resource>https://www.isca-archive.org/blizzard_2023/qi23_blizzard.html</resource>
					</doi_data>
				</conference_paper>
				<conference_paper publication_type="full_text">
					<contributors>
						<person_name sequence="first" contributor_role="author">
<given_name>Félix</given_name>
<surname>Saget</surname>
</person_name><person_name sequence="additional" contributor_role="author">
<given_name>Thibault</given_name>
<surname>Gaudier</surname>
</person_name><person_name sequence="additional" contributor_role="author">
<given_name>Meysam</given_name>
<surname>Shamsi</surname>
</person_name><person_name sequence="additional" contributor_role="author">
<given_name>Marie</given_name>
<surname>Tahon</surname>
</person_name>
					</contributors>
					<titles><title>LIUM-TTS entry for Blizzard 2023</title></titles>
					<publication_date media_type='online'>
						<month>8</month>
						<day>29</day>
						<year>2023</year>
					</publication_date>
					<pages>
						<first_page>28</first_page>
						<last_page>33</last_page>
					</pages>
					<doi_data>
						<doi>10.21437/Blizzard.2023-2</doi>
						<resource>https://www.isca-archive.org/blizzard_2023/saget23_blizzard.html</resource>
					</doi_data>
				</conference_paper>
				<conference_paper publication_type="full_text">
					<contributors>
						<person_name sequence="first" contributor_role="author">
<given_name>Zengqiang</given_name>
<surname>Shang</surname>
</person_name><person_name sequence="additional" contributor_role="author">
<given_name>Xuyuan</given_name>
<surname>Li</surname>
</person_name><person_name sequence="additional" contributor_role="author">
<given_name>Peiyang</given_name>
<surname>Shi</surname>
</person_name><person_name sequence="additional" contributor_role="author">
<given_name>Hua</given_name>
<surname>Hua</surname>
</person_name><person_name sequence="additional" contributor_role="author">
<given_name>Pengyuan</given_name>
<surname>Zhang</surname>
</person_name>
					</contributors>
					<titles><title>The IOA-ThinkIT system for Blizzard Challenge 2023</title></titles>
					<publication_date media_type='online'>
						<month>8</month>
						<day>29</day>
						<year>2023</year>
					</publication_date>
					<pages>
						<first_page>124</first_page>
						<last_page>129</last_page>
					</pages>
					<doi_data>
						<doi>10.21437/Blizzard.2023-19</doi>
						<resource>https://www.isca-archive.org/blizzard_2023/shang23_blizzard.html</resource>
					</doi_data>
				</conference_paper>
				<conference_paper publication_type="full_text">
					<contributors>
						<person_name sequence="first" contributor_role="author">
<given_name>Christophe</given_name>
<surname>Veaux</surname>
</person_name><person_name sequence="additional" contributor_role="author">
<given_name>Ranniery</given_name>
<surname>Maia</surname>
</person_name><person_name sequence="additional" contributor_role="author">
<given_name>Spyridoula</given_name>
<surname>Papendreou</surname>
</person_name>
					</contributors>
					<titles><title>The DeepZen Speech Synthesis System for Blizzard Challenge 2023</title></titles>
					<publication_date media_type='online'>
						<month>8</month>
						<day>29</day>
						<year>2023</year>
					</publication_date>
					<pages>
						<first_page>81</first_page>
						<last_page>86</last_page>
					</pages>
					<doi_data>
						<doi>10.21437/Blizzard.2023-11</doi>
						<resource>https://www.isca-archive.org/blizzard_2023/veaux23_blizzard.html</resource>
					</doi_data>
				</conference_paper>
				<conference_paper publication_type="full_text">
					<contributors>
						<person_name sequence="first" contributor_role="author">
<given_name>Kun</given_name>
<surname>Xie</surname>
</person_name><person_name sequence="additional" contributor_role="author">
<given_name>Yi-Chen</given_name>
<surname>Wu</surname>
</person_name><person_name sequence="additional" contributor_role="author">
<given_name>Feng-Long</given_name>
<surname>Xie</surname>
</person_name>
					</contributors>
					<titles><title>FireRedTTS: The Xiaohongshu Speech Synthesis System for Blizzard Challenge 2023</title></titles>
					<publication_date media_type='online'>
						<month>8</month>
						<day>29</day>
						<year>2023</year>
					</publication_date>
					<pages>
						<first_page>87</first_page>
						<last_page>92</last_page>
					</pages>
					<doi_data>
						<doi>10.21437/Blizzard.2023-12</doi>
						<resource>https://www.isca-archive.org/blizzard_2023/xie23_blizzard.html</resource>
					</doi_data>
				</conference_paper>
				<conference_paper publication_type="full_text">
					<contributors>
						<person_name sequence="first" contributor_role="author">
<given_name>Zhihang</given_name>
<surname>Xie</surname>
</person_name><person_name sequence="additional" contributor_role="author">
<given_name>Rui</given_name>
<surname>Fang</surname>
</person_name><person_name sequence="additional" contributor_role="author">
<given_name>Mingtian</given_name>
<surname>Zhao</surname>
</person_name>
					</contributors>
					<titles><title>The BIGAI Text-to-Speech Systems for Blizzard Challenge 2023</title></titles>
					<publication_date media_type='online'>
						<month>8</month>
						<day>29</day>
						<year>2023</year>
					</publication_date>
					<pages>
						<first_page>98</first_page>
						<last_page>102</last_page>
					</pages>
					<doi_data>
						<doi>10.21437/Blizzard.2023-14</doi>
						<resource>https://www.isca-archive.org/blizzard_2023/xie23b_blizzard.html</resource>
					</doi_data>
				</conference_paper>
				<conference_paper publication_type="full_text">
					<contributors>
						<person_name sequence="first" contributor_role="author">
<given_name>Zhihang</given_name>
<surname>Xu</surname>
</person_name><person_name sequence="additional" contributor_role="author">
<given_name>Shaofei</given_name>
<surname>Zhang</surname>
</person_name><person_name sequence="additional" contributor_role="author">
<given_name>Xi</given_name>
<surname>Wang</surname>
</person_name><person_name sequence="additional" contributor_role="author">
<given_name>Jiajun</given_name>
<surname>Zhang</surname>
</person_name><person_name sequence="additional" contributor_role="author">
<given_name>Wenning</given_name>
<surname>Wei</surname>
</person_name><person_name sequence="additional" contributor_role="author">
<given_name>Lei</given_name>
<surname>He</surname>
</person_name><person_name sequence="additional" contributor_role="author">
<given_name>Sheng</given_name>
<surname>Zhao</surname>
</person_name>
					</contributors>
					<titles><title>MuLanTTS: The Microsoft Speech Synthesis System for Blizzard Challenge 2023</title></titles>
					<publication_date media_type='online'>
						<month>8</month>
						<day>29</day>
						<year>2023</year>
					</publication_date>
					<pages>
						<first_page>46</first_page>
						<last_page>51</last_page>
					</pages>
					<doi_data>
						<doi>10.21437/Blizzard.2023-5</doi>
						<resource>https://www.isca-archive.org/blizzard_2023/xu23_blizzard.html</resource>
					</doi_data>
				</conference_paper>
				<conference_paper publication_type="full_text">
					<contributors>
						<person_name sequence="first" contributor_role="author">
<given_name>Julian</given_name>
<surname>Zaïdi</surname>
</person_name><person_name sequence="additional" contributor_role="author">
<given_name>Corentin</given_name>
<surname>Duchêne</surname>
</person_name><person_name sequence="additional" contributor_role="author">
<given_name>Hugo</given_name>
<surname>Seuté</surname>
</person_name><person_name sequence="additional" contributor_role="author">
<given_name>Marc-André</given_name>
<surname>Carbonneau</surname>
</person_name>
					</contributors>
					<titles><title>The La Forge Speech Synthesis System for Blizzard Challenge 2023</title></titles>
					<publication_date media_type='online'>
						<month>8</month>
						<day>29</day>
						<year>2023</year>
					</publication_date>
					<pages>
						<first_page>75</first_page>
						<last_page>80</last_page>
					</pages>
					<doi_data>
						<doi>10.21437/Blizzard.2023-10</doi>
						<resource>https://www.isca-archive.org/blizzard_2023/zaidi23_blizzard.html</resource>
					</doi_data>
				</conference_paper>
				<conference_paper publication_type="full_text">
					<contributors>
						<person_name sequence="first" contributor_role="author">
<given_name>Frank</given_name>
<surname>Zalkow</surname>
</person_name><person_name sequence="additional" contributor_role="author">
<given_name>Paolo</given_name>
<surname>Sani</surname>
</person_name><person_name sequence="additional" contributor_role="author">
<given_name>Michael</given_name>
<surname>Fast</surname>
</person_name><person_name sequence="additional" contributor_role="author">
<given_name>Judith</given_name>
<surname>Bauer</surname>
</person_name><person_name sequence="additional" contributor_role="author">
<given_name>Mohammad</given_name>
<surname>Joshaghani</surname>
</person_name><person_name sequence="additional" contributor_role="author">
<given_name>Kishor Kayyar</given_name>
<surname>Lakshminarayana</surname>
</person_name><person_name sequence="additional" contributor_role="author">
<given_name>Emanuël A. P.</given_name>
<surname>Habets</surname>
</person_name><person_name sequence="additional" contributor_role="author">
<given_name>Christian</given_name>
<surname>Dittmar</surname>
</person_name>
					</contributors>
					<titles><title>The AudioLabs System for the Blizzard Challenge 2023</title></titles>
					<publication_date media_type='online'>
						<month>8</month>
						<day>29</day>
						<year>2023</year>
					</publication_date>
					<pages>
						<first_page>63</first_page>
						<last_page>68</last_page>
					</pages>
					<doi_data>
						<doi>10.21437/Blizzard.2023-8</doi>
						<resource>https://www.isca-archive.org/blizzard_2023/zalkow23_blizzard.html</resource>
					</doi_data>
				</conference_paper>
		</conference>
	</body>
</doi_batch>