<doi_batch xmlns="http://www.crossref.org/schema/4.3.7" xmlns:xsi="http://www.w3.org/2001/XMLSchema-instance" xsi:schemaLocation="http://www.crossref.org/schema/4.3.7 http://www.crossref.org/schemas/crossref4.3.7.xsd" version="4.3.7">
	<head>
		<doi_batch_id>odyssey_2022</doi_batch_id>
		<timestamp>1705401533591037</timestamp>
		<depositor>
			<depositor_name>Martin Cooke</depositor_name> 
			<email_address>m.cooke@ikerbasque.org</email_address>
		</depositor>
		<registrant>International Speech Communication Association</registrant> 
	</head>
	<body>
		<conference>
			<event_metadata>
				<conference_name>The Speaker and Language Recognition Workshop (Odyssey 2022)</conference_name>
				<conference_acronym>odyssey_2022</conference_acronym>
				<conference_date>28 June - 1 July 2022</conference_date>
			</event_metadata>
			<proceedings_metadata language="en">
				<proceedings_title>The Speaker and Language Recognition Workshop (Odyssey 2022)</proceedings_title>
				<publisher>
					<publisher_name>ISCA</publisher_name>
					<publisher_place>ISCA</publisher_place>
				</publisher>
				<publication_date>
					<year>2022</year>
				</publication_date>
				<noisbn reason='simple_series'/>
				<doi_data>
					<doi>10.21437/Odyssey.2022</doi>
					<timestamp>1705401533591037</timestamp>
					<resource>https://www.isca-archive.org/odyssey_2022/</resource>
				</doi_data>
			</proceedings_metadata>
				<conference_paper publication_type="full_text">
					<contributors>
						<person_name sequence="first" contributor_role="author">
<given_name>Xin</given_name>
<surname>Wang</surname>
</person_name><person_name sequence="additional" contributor_role="author">
<given_name>Junichi</given_name>
<surname>Yamagishi</surname>
</person_name>
					</contributors>
					<titles><title>Investigating Self-Supervised Front Ends for Speech Spoofing Countermeasures</title></titles>
					<publication_date media_type='online'>
						<month>6</month>
						<day>28</day>
						<year>2022</year>
					</publication_date>
					<pages>
						<first_page>100</first_page>
						<last_page>106</last_page>
					</pages>
					<doi_data>
						<doi>10.21437/Odyssey.2022-14</doi>
						<resource>https://www.isca-archive.org/odyssey_2022/wang22_odyssey.html</resource>
					</doi_data>
				</conference_paper>
				<conference_paper publication_type="full_text">
					<contributors>
						<person_name sequence="first" contributor_role="author">
<given_name>Junyi</given_name>
<surname>Peng</surname>
</person_name><person_name sequence="additional" contributor_role="author">
<given_name>Chunlei</given_name>
<surname>Zhang</surname>
</person_name><person_name sequence="additional" contributor_role="author">
<given_name>Jan "Honza"</given_name>
<surname>Černocký</surname>
</person_name><person_name sequence="additional" contributor_role="author">
<given_name>Dong</given_name>
<surname>Yu</surname>
</person_name>
					</contributors>
					<titles><title>Progressive Contrastive Learning for Self-Supervised Text-Independent Speaker Verification</title></titles>
					<publication_date media_type='online'>
						<month>6</month>
						<day>28</day>
						<year>2022</year>
					</publication_date>
					<pages>
						<first_page>17</first_page>
						<last_page>24</last_page>
					</pages>
					<doi_data>
						<doi>10.21437/Odyssey.2022-3</doi>
						<resource>https://www.isca-archive.org/odyssey_2022/peng22_odyssey.html</resource>
					</doi_data>
				</conference_paper>
				<conference_paper publication_type="full_text">
					<contributors>
						<person_name sequence="first" contributor_role="author">
<given_name>Natsuo</given_name>
<surname>Yamashita</surname>
</person_name><person_name sequence="additional" contributor_role="author">
<given_name>Shota</given_name>
<surname>Horiguchi</surname>
</person_name><person_name sequence="additional" contributor_role="author">
<given_name>Takeshi</given_name>
<surname>Homma</surname>
</person_name>
					</contributors>
					<titles><title>Improving the Naturalness of Simulated Conversations for End-to-End Neural Diarization</title></titles>
					<publication_date media_type='online'>
						<month>6</month>
						<day>28</day>
						<year>2022</year>
					</publication_date>
					<pages>
						<first_page>133</first_page>
						<last_page>140</last_page>
					</pages>
					<doi_data>
						<doi>10.21437/Odyssey.2022-19</doi>
						<resource>https://www.isca-archive.org/odyssey_2022/yamashita22_odyssey.html</resource>
					</doi_data>
				</conference_paper>
				<conference_paper publication_type="full_text">
					<contributors>
						<person_name sequence="first" contributor_role="author">
<given_name>Woo Hyun</given_name>
<surname>Kang</surname>
</person_name><person_name sequence="additional" contributor_role="author">
<given_name>Jahangir</given_name>
<surname>Alam</surname>
</person_name><person_name sequence="additional" contributor_role="author">
<given_name>Abderrahim</given_name>
<surname>Fathan</surname>
</person_name>
					</contributors>
					<titles><title>Investigation on Mixup Strategies for End-to-End Voice Spoof Detection System</title></titles>
					<publication_date media_type='online'>
						<month>6</month>
						<day>28</day>
						<year>2022</year>
					</publication_date>
					<pages>
						<first_page>55</first_page>
						<last_page>61</last_page>
					</pages>
					<doi_data>
						<doi>10.21437/Odyssey.2022-8</doi>
						<resource>https://www.isca-archive.org/odyssey_2022/kang22_odyssey.html</resource>
					</doi_data>
				</conference_paper>
				<conference_paper publication_type="full_text">
					<contributors>
						<person_name sequence="first" contributor_role="author">
<given_name>Yijun</given_name>
<surname>Gong</surname>
</person_name><person_name sequence="additional" contributor_role="author">
<given_name>Xiao-Lei</given_name>
<surname>Zhang</surname>
</person_name>
					</contributors>
					<titles><title>DP-Means: An Efficient Bayesian Nonparametric Model for Speaker Diarization</title></titles>
					<publication_date media_type='online'>
						<month>6</month>
						<day>28</day>
						<year>2022</year>
					</publication_date>
					<pages>
						<first_page>156</first_page>
						<last_page>161</last_page>
					</pages>
					<doi_data>
						<doi>10.21437/Odyssey.2022-22</doi>
						<resource>https://www.isca-archive.org/odyssey_2022/gong22_odyssey.html</resource>
					</doi_data>
				</conference_paper>
				<conference_paper publication_type="full_text">
					<contributors>
						<person_name sequence="first" contributor_role="author">
<given_name>Diego</given_name>
<surname>Castan</surname>
</person_name><person_name sequence="additional" contributor_role="author">
<given_name>Md Hafizur</given_name>
<surname>Rahman</surname>
</person_name><person_name sequence="additional" contributor_role="author">
<given_name>Sarah</given_name>
<surname>Bakst</surname>
</person_name><person_name sequence="additional" contributor_role="author">
<given_name>Chris</given_name>
<surname>Cobo-Kroenke</surname>
</person_name><person_name sequence="additional" contributor_role="author">
<given_name>Mitchell</given_name>
<surname>McLaren</surname>
</person_name><person_name sequence="additional" contributor_role="author">
<given_name>Martin</given_name>
<surname>Graciarena</surname>
</person_name><person_name sequence="additional" contributor_role="author">
<given_name>Aaron</given_name>
<surname>Lawson</surname>
</person_name>
					</contributors>
					<titles><title>Speaker-Targeted Synthetic Speech Detection</title></titles>
					<publication_date media_type='online'>
						<month>6</month>
						<day>28</day>
						<year>2022</year>
					</publication_date>
					<pages>
						<first_page>62</first_page>
						<last_page>69</last_page>
					</pages>
					<doi_data>
						<doi>10.21437/Odyssey.2022-9</doi>
						<resource>https://www.isca-archive.org/odyssey_2022/castan22_odyssey.html</resource>
					</doi_data>
				</conference_paper>
				<conference_paper publication_type="full_text">
					<contributors>
						<person_name sequence="first" contributor_role="author">
<given_name>Xiaoxiao</given_name>
<surname>Miao</surname>
</person_name><person_name sequence="additional" contributor_role="author">
<given_name>Xin</given_name>
<surname>Wang</surname>
</person_name><person_name sequence="additional" contributor_role="author">
<given_name>Erica</given_name>
<surname>Cooper</surname>
</person_name><person_name sequence="additional" contributor_role="author">
<given_name>Junichi</given_name>
<surname>Yamagishi</surname>
</person_name><person_name sequence="additional" contributor_role="author">
<given_name>Natalia</given_name>
<surname>Tomashenko</surname>
</person_name>
					</contributors>
					<titles><title>Language-Independent Speaker Anonymization Approach Using Self-Supervised Pre-Trained Models</title></titles>
					<publication_date media_type='online'>
						<month>6</month>
						<day>28</day>
						<year>2022</year>
					</publication_date>
					<pages>
						<first_page>279</first_page>
						<last_page>286</last_page>
					</pages>
					<doi_data>
						<doi>10.21437/Odyssey.2022-39</doi>
						<resource>https://www.isca-archive.org/odyssey_2022/miao22_odyssey.html</resource>
					</doi_data>
				</conference_paper>
				<conference_paper publication_type="full_text">
					<contributors>
						<person_name sequence="first" contributor_role="author">
<given_name>Yucong</given_name>
<surname>Zhang</surname>
</person_name><person_name sequence="additional" contributor_role="author">
<given_name>Qinjian</given_name>
<surname>Lin</surname>
</person_name><person_name sequence="additional" contributor_role="author">
<given_name>Weiqing</given_name>
<surname>Wang</surname>
</person_name><person_name sequence="additional" contributor_role="author">
<given_name>Lin</given_name>
<surname>Yang</surname>
</person_name><person_name sequence="additional" contributor_role="author">
<given_name>Xuyang</given_name>
<surname>Wang</surname>
</person_name><person_name sequence="additional" contributor_role="author">
<given_name>Junjie</given_name>
<surname>Wang</surname>
</person_name><person_name sequence="additional" contributor_role="author">
<given_name>Ming</given_name>
<surname>Li</surname>
</person_name>
					</contributors>
					<titles><title>Low-Latency Online Speaker Diarization with Graph-Based Label Generation</title></titles>
					<publication_date media_type='online'>
						<month>6</month>
						<day>28</day>
						<year>2022</year>
					</publication_date>
					<pages>
						<first_page>162</first_page>
						<last_page>169</last_page>
					</pages>
					<doi_data>
						<doi>10.21437/Odyssey.2022-23</doi>
						<resource>https://www.isca-archive.org/odyssey_2022/zhang22_odyssey.html</resource>
					</doi_data>
				</conference_paper>
				<conference_paper publication_type="full_text">
					<contributors>
						<person_name sequence="first" contributor_role="author">
<given_name>Sandro</given_name>
<surname>Cumani</surname>
</person_name><person_name sequence="additional" contributor_role="author">
<given_name>Salvatore</given_name>
<surname>Sarni</surname>
</person_name>
					</contributors>
					<titles><title>Impostor Score Statistics as Quality Measures for the Calibration of Speaker Verification Systems</title></titles>
					<publication_date media_type='online'>
						<month>6</month>
						<day>28</day>
						<year>2022</year>
					</publication_date>
					<pages>
						<first_page>25</first_page>
						<last_page>32</last_page>
					</pages>
					<doi_data>
						<doi>10.21437/Odyssey.2022-4</doi>
						<resource>https://www.isca-archive.org/odyssey_2022/cumani22_odyssey.html</resource>
					</doi_data>
				</conference_paper>
				<conference_paper publication_type="full_text">
					<contributors>
						<person_name sequence="first" contributor_role="author">
<given_name>Quan</given_name>
<surname>Wang</surname>
</person_name><person_name sequence="additional" contributor_role="author">
<given_name>Yang</given_name>
<surname>Yu</surname>
</person_name><person_name sequence="additional" contributor_role="author">
<given_name>Jason</given_name>
<surname>Pelecanos</surname>
</person_name><person_name sequence="additional" contributor_role="author">
<given_name>Yiling</given_name>
<surname>Huang</surname>
</person_name><person_name sequence="additional" contributor_role="author">
<given_name>Ignacio Lopez</given_name>
<surname>Moreno</surname>
</person_name>
					</contributors>
					<titles><title>Attentive Temporal Pooling for Conformer-Based Streaming Language Identification in Long-Form Speech</title></titles>
					<publication_date media_type='online'>
						<month>6</month>
						<day>28</day>
						<year>2022</year>
					</publication_date>
					<pages>
						<first_page>255</first_page>
						<last_page>262</last_page>
					</pages>
					<doi_data>
						<doi>10.21437/Odyssey.2022-36</doi>
						<resource>https://www.isca-archive.org/odyssey_2022/wang22b_odyssey.html</resource>
					</doi_data>
				</conference_paper>
				<conference_paper publication_type="full_text">
					<contributors>
						<person_name sequence="first" contributor_role="author">
<given_name>Rajeev</given_name>
<surname>Rikhye</surname>
</person_name><person_name sequence="additional" contributor_role="author">
<given_name>Quan</given_name>
<surname>Wang</surname>
</person_name><person_name sequence="additional" contributor_role="author">
<given_name>Qiao</given_name>
<surname>Liang</surname>
</person_name><person_name sequence="additional" contributor_role="author">
<given_name>Yanzhang</given_name>
<surname>He</surname>
</person_name><person_name sequence="additional" contributor_role="author">
<given_name>Ian</given_name>
<surname>McGraw</surname>
</person_name>
					</contributors>
					<titles><title>Closing the Gap Between Single-User and Multi-User VoiceFilter-Lite</title></titles>
					<publication_date media_type='online'>
						<month>6</month>
						<day>28</day>
						<year>2022</year>
					</publication_date>
					<pages>
						<first_page>294</first_page>
						<last_page>300</last_page>
					</pages>
					<doi_data>
						<doi>10.21437/Odyssey.2022-41</doi>
						<resource>https://www.isca-archive.org/odyssey_2022/rikhye22_odyssey.html</resource>
					</doi_data>
				</conference_paper>
				<conference_paper publication_type="full_text">
					<contributors>
						<person_name sequence="first" contributor_role="author">
<given_name>Sarala</given_name>
<surname>Padi</surname>
</person_name><person_name sequence="additional" contributor_role="author">
<given_name>Seyed Omid</given_name>
<surname>Sadjadi</surname>
</person_name><person_name sequence="additional" contributor_role="author">
<given_name>Dinesh</given_name>
<surname>Manocha</surname>
</person_name><person_name sequence="additional" contributor_role="author">
<given_name>Ram D.</given_name>
<surname>Sriram</surname>
</person_name>
					</contributors>
					<titles><title>Multimodal Emotion Recognition Using Transfer Learning from Speaker Recognition and BERT-Based Models</title></titles>
					<publication_date media_type='online'>
						<month>6</month>
						<day>28</day>
						<year>2022</year>
					</publication_date>
					<pages>
						<first_page>407</first_page>
						<last_page>414</last_page>
					</pages>
					<doi_data>
						<doi>10.21437/Odyssey.2022-57</doi>
						<resource>https://www.isca-archive.org/odyssey_2022/padi22_odyssey.html</resource>
					</doi_data>
				</conference_paper>
				<conference_paper publication_type="full_text">
					<contributors>
						<person_name sequence="first" contributor_role="author">
<given_name>Jason</given_name>
<surname>Pelecanos</surname>
</person_name><person_name sequence="additional" contributor_role="author">
<given_name>Quan</given_name>
<surname>Wang</surname>
</person_name><person_name sequence="additional" contributor_role="author">
<given_name>Yiling</given_name>
<surname>Huang</surname>
</person_name><person_name sequence="additional" contributor_role="author">
<given_name>Ignacio Lopez</given_name>
<surname>Moreno</surname>
</person_name>
					</contributors>
					<titles><title>Parameter-Free Attentive Scoring for Speaker Verification</title></titles>
					<publication_date media_type='online'>
						<month>6</month>
						<day>28</day>
						<year>2022</year>
					</publication_date>
					<pages>
						<first_page>200</first_page>
						<last_page>206</last_page>
					</pages>
					<doi_data>
						<doi>10.21437/Odyssey.2022-28</doi>
						<resource>https://www.isca-archive.org/odyssey_2022/pelecanos22_odyssey.html</resource>
					</doi_data>
				</conference_paper>
				<conference_paper publication_type="full_text">
					<contributors>
						<person_name sequence="first" contributor_role="author">
<given_name>Wei</given_name>
<surname>Liu</surname>
</person_name><person_name sequence="additional" contributor_role="author">
<given_name>Meng</given_name>
<surname>Sun</surname>
</person_name><person_name sequence="additional" contributor_role="author">
<given_name>Xiongwei</given_name>
<surname>Zhang</surname>
</person_name><person_name sequence="additional" contributor_role="author">
<given_name>Hugo Van</given_name>
<surname>hamme</surname>
</person_name><person_name sequence="additional" contributor_role="author">
<given_name>Thomas Fang</given_name>
<surname>Zheng</surname>
</person_name>
					</contributors>
					<titles><title>A Multi-Resolution Front-End for End-to-End Speech Anti-Spoofing</title></titles>
					<publication_date media_type='online'>
						<month>6</month>
						<day>28</day>
						<year>2022</year>
					</publication_date>
					<pages>
						<first_page>120</first_page>
						<last_page>125</last_page>
					</pages>
					<doi_data>
						<doi>10.21437/Odyssey.2022-17</doi>
						<resource>https://www.isca-archive.org/odyssey_2022/liu22_odyssey.html</resource>
					</doi_data>
				</conference_paper>
				<conference_paper publication_type="full_text">
					<contributors>
						<person_name sequence="first" contributor_role="author">
<given_name>Woo Hyun</given_name>
<surname>Kang</surname>
</person_name><person_name sequence="additional" contributor_role="author">
<given_name>Jahangir</given_name>
<surname>Alam</surname>
</person_name><person_name sequence="additional" contributor_role="author">
<given_name>Abderrahim</given_name>
<surname>Fathan</surname>
</person_name>
					</contributors>
					<titles><title>Domain Generalized Speaker Embedding Learning via Mutual Information Minimization</title></titles>
					<publication_date media_type='online'>
						<month>6</month>
						<day>28</day>
						<year>2022</year>
					</publication_date>
					<pages>
						<first_page>178</first_page>
						<last_page>184</last_page>
					</pages>
					<doi_data>
						<doi>10.21437/Odyssey.2022-25</doi>
						<resource>https://www.isca-archive.org/odyssey_2022/kang22b_odyssey.html</resource>
					</doi_data>
				</conference_paper>
				<conference_paper publication_type="full_text">
					<contributors>
						<person_name sequence="first" contributor_role="author">
<given_name>Tanel</given_name>
<surname>Alumäe</surname>
</person_name><person_name sequence="additional" contributor_role="author">
<given_name>Kunnar</given_name>
<surname>Kukk</surname>
</person_name>
					</contributors>
					<titles><title>Pretraining Approaches for Spoken Language Recognition: TalTech Submission to the OLR 2021 Challenge</title></titles>
					<publication_date media_type='online'>
						<month>6</month>
						<day>28</day>
						<year>2022</year>
					</publication_date>
					<pages>
						<first_page>240</first_page>
						<last_page>247</last_page>
					</pages>
					<doi_data>
						<doi>10.21437/Odyssey.2022-34</doi>
						<resource>https://www.isca-archive.org/odyssey_2022/alumae22_odyssey.html</resource>
					</doi_data>
				</conference_paper>
				<conference_paper publication_type="full_text">
					<contributors>
						<person_name sequence="first" contributor_role="author">
<given_name>Yanxiong</given_name>
<surname>Li</surname>
</person_name><person_name sequence="additional" contributor_role="author">
<given_name>Wucheng</given_name>
<surname>Wang</surname>
</person_name><person_name sequence="additional" contributor_role="author">
<given_name>Hao</given_name>
<surname>Chen</surname>
</person_name><person_name sequence="additional" contributor_role="author">
<given_name>Wenchang</given_name>
<surname>Cao</surname>
</person_name><person_name sequence="additional" contributor_role="author">
<given_name>Wei</given_name>
<surname>Li</surname>
</person_name><person_name sequence="additional" contributor_role="author">
<given_name>Qianhua</given_name>
<surname>He</surname>
</person_name>
					</contributors>
					<titles><title>Few-Shot Speaker Identification Using Depthwise Separable Convolutional Network with Channel Attention</title></titles>
					<publication_date media_type='online'>
						<month>6</month>
						<day>28</day>
						<year>2022</year>
					</publication_date>
					<pages>
						<first_page>221</first_page>
						<last_page>227</last_page>
					</pages>
					<doi_data>
						<doi>10.21437/Odyssey.2022-31</doi>
						<resource>https://www.isca-archive.org/odyssey_2022/li22_odyssey.html</resource>
					</doi_data>
				</conference_paper>
				<conference_paper publication_type="full_text">
					<contributors>
						<person_name sequence="first" contributor_role="author">
<given_name>Zuoer</given_name>
<surname>Chen</surname>
</person_name><person_name sequence="additional" contributor_role="author">
<given_name>Liang</given_name>
<surname>He</surname>
</person_name>
					</contributors>
					<titles><title>A Quick and Effective Speaker Diarization System</title></titles>
					<publication_date media_type='online'>
						<month>6</month>
						<day>28</day>
						<year>2022</year>
					</publication_date>
					<pages>
						<first_page>170</first_page>
						<last_page>177</last_page>
					</pages>
					<doi_data>
						<doi>10.21437/Odyssey.2022-24</doi>
						<resource>https://www.isca-archive.org/odyssey_2022/chen22_odyssey.html</resource>
					</doi_data>
				</conference_paper>
				<conference_paper publication_type="full_text">
					<contributors>
						<person_name sequence="first" contributor_role="author">
<given_name>Hiroto</given_name>
<surname>Kai</surname>
</person_name><person_name sequence="additional" contributor_role="author">
<given_name>Shinnosuke</given_name>
<surname>Takamichi</surname>
</person_name><person_name sequence="additional" contributor_role="author">
<given_name>Sayaka</given_name>
<surname>Shiota</surname>
</person_name><person_name sequence="additional" contributor_role="author">
<given_name>Hitoshi</given_name>
<surname>Kiya</surname>
</person_name>
					</contributors>
					<titles><title>Robustness of Signal Processing-Based Pseudonymization Method Against Decryption Attack</title></titles>
					<publication_date media_type='online'>
						<month>6</month>
						<day>28</day>
						<year>2022</year>
					</publication_date>
					<pages>
						<first_page>287</first_page>
						<last_page>293</last_page>
					</pages>
					<doi_data>
						<doi>10.21437/Odyssey.2022-40</doi>
						<resource>https://www.isca-archive.org/odyssey_2022/kai22_odyssey.html</resource>
					</doi_data>
				</conference_paper>
				<conference_paper publication_type="full_text">
					<contributors>
						<person_name sequence="first" contributor_role="author">
<given_name>Fuchuan</given_name>
<surname>Tong</surname>
</person_name><person_name sequence="additional" contributor_role="author">
<given_name>Siqi</given_name>
<surname>Zheng</surname>
</person_name><person_name sequence="additional" contributor_role="author">
<given_name>Haodong</given_name>
<surname>Zhou</surname>
</person_name><person_name sequence="additional" contributor_role="author">
<given_name>Xingjia</given_name>
<surname>Xie</surname>
</person_name><person_name sequence="additional" contributor_role="author">
<given_name>Qingyang</given_name>
<surname>Hong</surname>
</person_name><person_name sequence="additional" contributor_role="author">
<given_name>Lin</given_name>
<surname>Li</surname>
</person_name>
					</contributors>
					<titles><title>Deep Representation Decomposition for Rate-Invariant Speaker Verification</title></titles>
					<publication_date media_type='online'>
						<month>6</month>
						<day>28</day>
						<year>2022</year>
					</publication_date>
					<pages>
						<first_page>228</first_page>
						<last_page>232</last_page>
					</pages>
					<doi_data>
						<doi>10.21437/Odyssey.2022-32</doi>
						<resource>https://www.isca-archive.org/odyssey_2022/tong22_odyssey.html</resource>
					</doi_data>
				</conference_paper>
				<conference_paper publication_type="full_text">
					<contributors>
						<person_name sequence="first" contributor_role="author">
<given_name>Sarah</given_name>
<surname>Bakst</surname>
</person_name><person_name sequence="additional" contributor_role="author">
<given_name>Chris</given_name>
<surname>Cobo-Kroenke</surname>
</person_name><person_name sequence="additional" contributor_role="author">
<given_name>Aaron</given_name>
<surname>Lawson</surname>
</person_name><person_name sequence="additional" contributor_role="author">
<given_name>Mitchell</given_name>
<surname>McLaren</surname>
</person_name><person_name sequence="additional" contributor_role="author">
<given_name>Allen</given_name>
<surname>Stauffer</surname>
</person_name>
					</contributors>
					<titles><title>Time-Varying Score Reliability Prediction in Speaker Identification</title></titles>
					<publication_date media_type='online'>
						<month>6</month>
						<day>28</day>
						<year>2022</year>
					</publication_date>
					<pages>
						<first_page>207</first_page>
						<last_page>212</last_page>
					</pages>
					<doi_data>
						<doi>10.21437/Odyssey.2022-29</doi>
						<resource>https://www.isca-archive.org/odyssey_2022/bakst22_odyssey.html</resource>
					</doi_data>
				</conference_paper>
				<conference_paper publication_type="full_text">
					<contributors>
						<person_name sequence="first" contributor_role="author">
<given_name>Heinrich</given_name>
<surname>Dinkel</surname>
</person_name><person_name sequence="additional" contributor_role="author">
<given_name>Zhiyong</given_name>
<surname>Yan</surname>
</person_name><person_name sequence="additional" contributor_role="author">
<given_name>Yongqing</given_name>
<surname>Wang</surname>
</person_name><person_name sequence="additional" contributor_role="author">
<given_name>Junbo</given_name>
<surname>Zhang</surname>
</person_name><person_name sequence="additional" contributor_role="author">
<given_name>Yujun</given_name>
<surname>Wang</surname>
</person_name>
					</contributors>
					<titles><title>An Empirical Study of Weakly Supervised Audio Tagging Embeddings for General Audio Representations</title></titles>
					<publication_date media_type='online'>
						<month>6</month>
						<day>28</day>
						<year>2022</year>
					</publication_date>
					<pages>
						<first_page>390</first_page>
						<last_page>395</last_page>
					</pages>
					<doi_data>
						<doi>10.21437/Odyssey.2022-54</doi>
						<resource>https://www.isca-archive.org/odyssey_2022/dinkel22_odyssey.html</resource>
					</doi_data>
				</conference_paper>
				<conference_paper publication_type="full_text">
					<contributors>
						<person_name sequence="first" contributor_role="author">
<given_name>Seyed Omid</given_name>
<surname>Sadjadi</surname>
</person_name><person_name sequence="additional" contributor_role="author">
<given_name>Craig</given_name>
<surname>Greenberg</surname>
</person_name><person_name sequence="additional" contributor_role="author">
<given_name>Elliot</given_name>
<surname>Singer</surname>
</person_name><person_name sequence="additional" contributor_role="author">
<given_name>Lisa</given_name>
<surname>Mason</surname>
</person_name><person_name sequence="additional" contributor_role="author">
<given_name>Douglas</given_name>
<surname>Reynolds</surname>
</person_name>
					</contributors>
					<titles><title>The NIST CTS Speaker Recognition Challenge</title></titles>
					<publication_date media_type='online'>
						<month>6</month>
						<day>28</day>
						<year>2022</year>
					</publication_date>
					<pages>
						<first_page>314</first_page>
						<last_page>321</last_page>
					</pages>
					<doi_data>
						<doi>10.21437/Odyssey.2022-44</doi>
						<resource>https://www.isca-archive.org/odyssey_2022/sadjadi22_odyssey.html</resource>
					</doi_data>
				</conference_paper>
				<conference_paper publication_type="full_text">
					<contributors>
						<person_name sequence="first" contributor_role="author">
<given_name>Seyed Omid</given_name>
<surname>Sadjadi</surname>
</person_name><person_name sequence="additional" contributor_role="author">
<given_name>Craig</given_name>
<surname>Greenberg</surname>
</person_name><person_name sequence="additional" contributor_role="author">
<given_name>Elliot</given_name>
<surname>Singer</surname>
</person_name><person_name sequence="additional" contributor_role="author">
<given_name>Lisa</given_name>
<surname>Mason</surname>
</person_name><person_name sequence="additional" contributor_role="author">
<given_name>Douglas</given_name>
<surname>Reynolds</surname>
</person_name>
					</contributors>
					<titles><title>The 2021 NIST Speaker Recognition Evaluation</title></titles>
					<publication_date media_type='online'>
						<month>6</month>
						<day>28</day>
						<year>2022</year>
					</publication_date>
					<pages>
						<first_page>322</first_page>
						<last_page>329</last_page>
					</pages>
					<doi_data>
						<doi>10.21437/Odyssey.2022-45</doi>
						<resource>https://www.isca-archive.org/odyssey_2022/sadjadi22b_odyssey.html</resource>
					</doi_data>
				</conference_paper>
				<conference_paper publication_type="full_text">
					<contributors>
						<person_name sequence="first" contributor_role="author">
<given_name>David</given_name>
<surname>Guennec</surname>
</person_name><person_name sequence="additional" contributor_role="author">
<given_name>Hassan</given_name>
<surname>Hajipoor</surname>
</person_name><person_name sequence="additional" contributor_role="author">
<given_name>Gwénolé</given_name>
<surname>Lecorvé</surname>
</person_name><person_name sequence="additional" contributor_role="author">
<given_name>Pascal</given_name>
<surname>Lintanf</surname>
</person_name><person_name sequence="additional" contributor_role="author">
<given_name>Damien</given_name>
<surname>Lolive</surname>
</person_name><person_name sequence="additional" contributor_role="author">
<given_name>Antoine</given_name>
<surname>Perquin</surname>
</person_name><person_name sequence="additional" contributor_role="author">
<given_name>Gaëlle</given_name>
<surname>Vidal</surname>
</person_name>
					</contributors>
					<titles><title>BreizhCorpus: A Large Breton Language Speech Corpus and Its Use for Text-to-Speech Synthesis</title></titles>
					<publication_date media_type='online'>
						<month>6</month>
						<day>28</day>
						<year>2022</year>
					</publication_date>
					<pages>
						<first_page>263</first_page>
						<last_page>270</last_page>
					</pages>
					<doi_data>
						<doi>10.21437/Odyssey.2022-37</doi>
						<resource>https://www.isca-archive.org/odyssey_2022/guennec22_odyssey.html</resource>
					</doi_data>
				</conference_paper>
				<conference_paper publication_type="full_text">
					<contributors>
						<person_name sequence="first" contributor_role="author">
<given_name>Lantian</given_name>
<surname>Li</surname>
</person_name><person_name sequence="additional" contributor_role="author">
<given_name>Di</given_name>
<surname>Wang</surname>
</person_name><person_name sequence="additional" contributor_role="author">
<given_name>Wenqiang</given_name>
<surname>Du</surname>
</person_name><person_name sequence="additional" contributor_role="author">
<given_name>Dong</given_name>
<surname>Wang</surname>
</person_name>
					</contributors>
					<titles><title>C-P Map: A Novel Evaluation Toolkit for Speaker Verification</title></titles>
					<publication_date media_type='online'>
						<month>6</month>
						<day>28</day>
						<year>2022</year>
					</publication_date>
					<pages>
						<first_page>306</first_page>
						<last_page>313</last_page>
					</pages>
					<doi_data>
						<doi>10.21437/Odyssey.2022-43</doi>
						<resource>https://www.isca-archive.org/odyssey_2022/li22b_odyssey.html</resource>
					</doi_data>
				</conference_paper>
				<conference_paper publication_type="full_text">
					<contributors>
						<person_name sequence="first" contributor_role="author">
<given_name>Hemlata</given_name>
<surname>Tak</surname>
</person_name><person_name sequence="additional" contributor_role="author">
<given_name>Massimiliano</given_name>
<surname>Todisco</surname>
</person_name><person_name sequence="additional" contributor_role="author">
<given_name>Xin</given_name>
<surname>Wang</surname>
</person_name><person_name sequence="additional" contributor_role="author">
<given_name>Jee-weon</given_name>
<surname>Jung</surname>
</person_name><person_name sequence="additional" contributor_role="author">
<given_name>Junichi</given_name>
<surname>Yamagishi</surname>
</person_name><person_name sequence="additional" contributor_role="author">
<given_name>Nicholas</given_name>
<surname>Evans</surname>
</person_name>
					</contributors>
					<titles><title>Automatic Speaker Verification Spoofing and Deepfake Detection Using Wav2vec 2.0 and Data Augmentation</title></titles>
					<publication_date media_type='online'>
						<month>6</month>
						<day>28</day>
						<year>2022</year>
					</publication_date>
					<pages>
						<first_page>112</first_page>
						<last_page>119</last_page>
					</pages>
					<doi_data>
						<doi>10.21437/Odyssey.2022-16</doi>
						<resource>https://www.isca-archive.org/odyssey_2022/tak22_odyssey.html</resource>
					</doi_data>
				</conference_paper>
				<conference_paper publication_type="full_text">
					<contributors>
						<person_name sequence="first" contributor_role="author">
<given_name>Alexey</given_name>
<surname>Sholokhov</surname>
</person_name><person_name sequence="additional" contributor_role="author">
<given_name>Xuechen</given_name>
<surname>Liu</surname>
</person_name><person_name sequence="additional" contributor_role="author">
<given_name>Md</given_name>
<surname>Sahidullah</surname>
</person_name><person_name sequence="additional" contributor_role="author">
<given_name>Tomi</given_name>
<surname>Kinnunen</surname>
</person_name>
					</contributors>
					<titles><title>Baselines and Protocols for Household Speaker Recognition</title></titles>
					<publication_date media_type='online'>
						<month>6</month>
						<day>28</day>
						<year>2022</year>
					</publication_date>
					<pages>
						<first_page>185</first_page>
						<last_page>192</last_page>
					</pages>
					<doi_data>
						<doi>10.21437/Odyssey.2022-26</doi>
						<resource>https://www.isca-archive.org/odyssey_2022/sholokhov22_odyssey.html</resource>
					</doi_data>
				</conference_paper>
				<conference_paper publication_type="full_text">
					<contributors>
						<person_name sequence="first" contributor_role="author">
<given_name>Wanying</given_name>
<surname>Ge</surname>
</person_name><person_name sequence="additional" contributor_role="author">
<given_name>Massimiliano</given_name>
<surname>Todisco</surname>
</person_name><person_name sequence="additional" contributor_role="author">
<given_name>Nicholas</given_name>
<surname>Evans</surname>
</person_name>
					</contributors>
					<titles><title>Explainable Deepfake and Spoofing Detection: An Attack Analysis Using SHapley Additive exPlanations</title></titles>
					<publication_date media_type='online'>
						<month>6</month>
						<day>28</day>
						<year>2022</year>
					</publication_date>
					<pages>
						<first_page>70</first_page>
						<last_page>76</last_page>
					</pages>
					<doi_data>
						<doi>10.21437/Odyssey.2022-10</doi>
						<resource>https://www.isca-archive.org/odyssey_2022/ge22_odyssey.html</resource>
					</doi_data>
				</conference_paper>
				<conference_paper publication_type="full_text">
					<contributors>
						<person_name sequence="first" contributor_role="author">
<given_name>Xuechen</given_name>
<surname>Liu</surname>
</person_name><person_name sequence="additional" contributor_role="author">
<given_name>Md</given_name>
<surname>Sahidullah</surname>
</person_name><person_name sequence="additional" contributor_role="author">
<given_name>Tomi</given_name>
<surname>Kinnunen</surname>
</person_name>
					</contributors>
					<titles><title>Spoofing-Aware Speaker Verification with Unsupervised Domain Adaptation</title></titles>
					<publication_date media_type='online'>
						<month>6</month>
						<day>28</day>
						<year>2022</year>
					</publication_date>
					<pages>
						<first_page>85</first_page>
						<last_page>91</last_page>
					</pages>
					<doi_data>
						<doi>10.21437/Odyssey.2022-12</doi>
						<resource>https://www.isca-archive.org/odyssey_2022/liu22b_odyssey.html</resource>
					</doi_data>
				</conference_paper>
				<conference_paper publication_type="full_text">
					<contributors>
						<person_name sequence="first" contributor_role="author">
<given_name>Jesús</given_name>
<surname>Villalba</surname>
</person_name><person_name sequence="additional" contributor_role="author">
<given_name>Bengt J.</given_name>
<surname>Borgstrom</surname>
</person_name><person_name sequence="additional" contributor_role="author">
<given_name>Saurabh</given_name>
<surname>Kataria</surname>
</person_name><person_name sequence="additional" contributor_role="author">
<given_name>Jaejin</given_name>
<surname>Cho</surname>
</person_name><person_name sequence="additional" contributor_role="author">
<given_name>Pedro A.</given_name>
<surname>Torres-Carrasquillo</surname>
</person_name><person_name sequence="additional" contributor_role="author">
<given_name>Najim</given_name>
<surname>Dehak</surname>
</person_name>
					</contributors>
					<titles><title>Advances in Speaker Recognition for Multilingual Conversational Telephone Speech: The JHU-MIT System for NIST SRE20 CTS Challenge</title></titles>
					<publication_date media_type='online'>
						<month>6</month>
						<day>28</day>
						<year>2022</year>
					</publication_date>
					<pages>
						<first_page>338</first_page>
						<last_page>345</last_page>
					</pages>
					<doi_data>
						<doi>10.21437/Odyssey.2022-47</doi>
						<resource>https://www.isca-archive.org/odyssey_2022/villalba22_odyssey.html</resource>
					</doi_data>
				</conference_paper>
				<conference_paper publication_type="full_text">
					<contributors>
						<person_name sequence="first" contributor_role="author">
<given_name>Jesús</given_name>
<surname>Villalba</surname>
</person_name><person_name sequence="additional" contributor_role="author">
<given_name>Bengt J.</given_name>
<surname>Borgstrom</surname>
</person_name><person_name sequence="additional" contributor_role="author">
<given_name>Saurabh</given_name>
<surname>Kataria</surname>
</person_name><person_name sequence="additional" contributor_role="author">
<given_name>Magdalena</given_name>
<surname>Rybicka</surname>
</person_name><person_name sequence="additional" contributor_role="author">
<given_name>Carlos D.</given_name>
<surname>Castillo</surname>
</person_name><person_name sequence="additional" contributor_role="author">
<given_name>Jaejin</given_name>
<surname>Cho</surname>
</person_name><person_name sequence="additional" contributor_role="author">
<given_name>L. Paola</given_name>
<surname>García-Perera</surname>
</person_name><person_name sequence="additional" contributor_role="author">
<given_name>Pedro A.</given_name>
<surname>Torres-Carrasquillo</surname>
</person_name><person_name sequence="additional" contributor_role="author">
<given_name>Najim</given_name>
<surname>Dehak</surname>
</person_name>
					</contributors>
					<titles><title>Advances in Cross-Lingual and Cross-Source Audio-Visual Speaker Recognition: The JHU-MIT System for NIST SRE21</title></titles>
					<publication_date media_type='online'>
						<month>6</month>
						<day>28</day>
						<year>2022</year>
					</publication_date>
					<pages>
						<first_page>213</first_page>
						<last_page>220</last_page>
					</pages>
					<doi_data>
						<doi>10.21437/Odyssey.2022-30</doi>
						<resource>https://www.isca-archive.org/odyssey_2022/villalba22b_odyssey.html</resource>
					</doi_data>
				</conference_paper>
				<conference_paper publication_type="full_text">
					<contributors>
						<person_name sequence="first" contributor_role="author">
<given_name>Hexin</given_name>
<surname>Liu</surname>
</person_name><person_name sequence="additional" contributor_role="author">
<given_name>Leibny Paola Garcia</given_name>
<surname>Perera</surname>
</person_name><person_name sequence="additional" contributor_role="author">
<given_name>Andy W. H.</given_name>
<surname>Khong</surname>
</person_name><person_name sequence="additional" contributor_role="author">
<given_name>Justin</given_name>
<surname>Dauwels</surname>
</person_name><person_name sequence="additional" contributor_role="author">
<given_name>Suzy J.</given_name>
<surname>Styles</surname>
</person_name><person_name sequence="additional" contributor_role="author">
<given_name>Sanjeev</given_name>
<surname>Khudanpur</surname>
</person_name>
					</contributors>
					<titles><title>Enhancing Language Identification Using Dual-Mode Model with Knowledge Distillation</title></titles>
					<publication_date media_type='online'>
						<month>6</month>
						<day>28</day>
						<year>2022</year>
					</publication_date>
					<pages>
						<first_page>248</first_page>
						<last_page>254</last_page>
					</pages>
					<doi_data>
						<doi>10.21437/Odyssey.2022-35</doi>
						<resource>https://www.isca-archive.org/odyssey_2022/liu22c_odyssey.html</resource>
					</doi_data>
				</conference_paper>
				<conference_paper publication_type="full_text">
					<contributors>
						<person_name sequence="first" contributor_role="author">
<given_name>Madina</given_name>
<surname>Abdrakhmanova</surname>
</person_name><person_name sequence="additional" contributor_role="author">
<given_name>Saniya</given_name>
<surname>Abushakimova</surname>
</person_name><person_name sequence="additional" contributor_role="author">
<given_name>Yerbolat</given_name>
<surname>Khassanov</surname>
</person_name><person_name sequence="additional" contributor_role="author">
<given_name>Huseyin Atakan</given_name>
<surname>Varol</surname>
</person_name>
					</contributors>
					<titles><title>A Study of Multimodal Person Verification Using Audio-Visual-Thermal Data</title></titles>
					<publication_date media_type='online'>
						<month>6</month>
						<day>28</day>
						<year>2022</year>
					</publication_date>
					<pages>
						<first_page>233</first_page>
						<last_page>239</last_page>
					</pages>
					<doi_data>
						<doi>10.21437/Odyssey.2022-33</doi>
						<resource>https://www.isca-archive.org/odyssey_2022/abdrakhmanova22_odyssey.html</resource>
					</doi_data>
				</conference_paper>
				<conference_paper publication_type="full_text">
					<contributors>
						<person_name sequence="first" contributor_role="author">
<given_name>Jingze</given_name>
<surname>Lu</surname>
</person_name><person_name sequence="additional" contributor_role="author">
<given_name>Yuxiang</given_name>
<surname>Zhang</surname>
</person_name><person_name sequence="additional" contributor_role="author">
<given_name>Wenchao</given_name>
<surname>Wang</surname>
</person_name><person_name sequence="additional" contributor_role="author">
<given_name>Pengyuan</given_name>
<surname>Zhang</surname>
</person_name>
					</contributors>
					<titles><title>Robust Cross-SubBand Countermeasure Against Replay Attacks</title></titles>
					<publication_date media_type='online'>
						<month>6</month>
						<day>28</day>
						<year>2022</year>
					</publication_date>
					<pages>
						<first_page>126</first_page>
						<last_page>132</last_page>
					</pages>
					<doi_data>
						<doi>10.21437/Odyssey.2022-18</doi>
						<resource>https://www.isca-archive.org/odyssey_2022/lu22_odyssey.html</resource>
					</doi_data>
				</conference_paper>
				<conference_paper publication_type="full_text">
					<contributors>
						<person_name sequence="first" contributor_role="author">
<given_name>Joonas</given_name>
<surname>Kalda</surname>
</person_name><person_name sequence="additional" contributor_role="author">
<given_name>Tanel</given_name>
<surname>Alumäe</surname>
</person_name>
					</contributors>
					<titles><title>Collar-Aware Training for Streaming Speaker Change Detection in Broadcast Speech</title></titles>
					<publication_date media_type='online'>
						<month>6</month>
						<day>28</day>
						<year>2022</year>
					</publication_date>
					<pages>
						<first_page>141</first_page>
						<last_page>147</last_page>
					</pages>
					<doi_data>
						<doi>10.21437/Odyssey.2022-20</doi>
						<resource>https://www.isca-archive.org/odyssey_2022/kalda22_odyssey.html</resource>
					</doi_data>
				</conference_paper>
				<conference_paper publication_type="full_text">
					<contributors>
						<person_name sequence="first" contributor_role="author">
<given_name>Galina</given_name>
<surname>Lavrentyeva</surname>
</person_name><person_name sequence="additional" contributor_role="author">
<given_name>Sergey</given_name>
<surname>Novoselov</surname>
</person_name><person_name sequence="additional" contributor_role="author">
<given_name>Vladimir</given_name>
<surname>Volokhov</surname>
</person_name><person_name sequence="additional" contributor_role="author">
<given_name>Anastasia</given_name>
<surname>Avdeeva</surname>
</person_name><person_name sequence="additional" contributor_role="author">
<given_name>Aleksei</given_name>
<surname>Gusev</surname>
</person_name><person_name sequence="additional" contributor_role="author">
<given_name>Alisa</given_name>
<surname>Vinogradova</surname>
</person_name><person_name sequence="additional" contributor_role="author">
<given_name>Igor</given_name>
<surname>Korsunov</surname>
</person_name><person_name sequence="additional" contributor_role="author">
<given_name>Alexander</given_name>
<surname>Kozlov</surname>
</person_name><person_name sequence="additional" contributor_role="author">
<given_name>Timur</given_name>
<surname>Pekhovsky</surname>
</person_name><person_name sequence="additional" contributor_role="author">
<given_name>Andrey</given_name>
<surname>Shulipa</surname>
</person_name><person_name sequence="additional" contributor_role="author">
<given_name>Evgeny</given_name>
<surname>Smirnov</surname>
</person_name><person_name sequence="additional" contributor_role="author">
<given_name>Vasily</given_name>
<surname>Galyuk</surname>
</person_name>
					</contributors>
					<titles><title>STC Speaker Recognition System for the NIST SRE 2021</title></titles>
					<publication_date media_type='online'>
						<month>6</month>
						<day>28</day>
						<year>2022</year>
					</publication_date>
					<pages>
						<first_page>354</first_page>
						<last_page>361</last_page>
					</pages>
					<doi_data>
						<doi>10.21437/Odyssey.2022-49</doi>
						<resource>https://www.isca-archive.org/odyssey_2022/lavrentyeva22_odyssey.html</resource>
					</doi_data>
				</conference_paper>
				<conference_paper publication_type="full_text">
					<contributors>
						<person_name sequence="first" contributor_role="author">
<given_name>Hye-jin</given_name>
<surname>Shim</surname>
</person_name><person_name sequence="additional" contributor_role="author">
<given_name>Hemlata</given_name>
<surname>Tak</surname>
</person_name><person_name sequence="additional" contributor_role="author">
<given_name>Xuechen</given_name>
<surname>Liu</surname>
</person_name><person_name sequence="additional" contributor_role="author">
<given_name>Hee-Soo</given_name>
<surname>Heo</surname>
</person_name><person_name sequence="additional" contributor_role="author">
<given_name>Jee-weon</given_name>
<surname>Jung</surname>
</person_name><person_name sequence="additional" contributor_role="author">
<given_name>Joon Son</given_name>
<surname>Chung</surname>
</person_name><person_name sequence="additional" contributor_role="author">
<given_name>Soo-Whan</given_name>
<surname>Chung</surname>
</person_name><person_name sequence="additional" contributor_role="author">
<given_name>Ha-Jin</given_name>
<surname>Yu</surname>
</person_name><person_name sequence="additional" contributor_role="author">
<given_name>Bong-Jin</given_name>
<surname>Lee</surname>
</person_name><person_name sequence="additional" contributor_role="author">
<given_name>Massimiliano</given_name>
<surname>Todisco</surname>
</person_name><person_name sequence="additional" contributor_role="author">
<given_name>Héctor</given_name>
<surname>Delgado</surname>
</person_name><person_name sequence="additional" contributor_role="author">
<given_name>Kong Aik</given_name>
<surname>Lee</surname>
</person_name><person_name sequence="additional" contributor_role="author">
<given_name>Md</given_name>
<surname>Sahidullah</surname>
</person_name><person_name sequence="additional" contributor_role="author">
<given_name>Tomi</given_name>
<surname>Kinnunen</surname>
</person_name><person_name sequence="additional" contributor_role="author">
<given_name>Nicholas</given_name>
<surname>Evans</surname>
</person_name>
					</contributors>
					<titles><title>Baseline Systems for the First Spoofing-Aware Speaker Verification Challenge: Score and Embedding Fusion</title></titles>
					<publication_date media_type='online'>
						<month>6</month>
						<day>28</day>
						<year>2022</year>
					</publication_date>
					<pages>
						<first_page>330</first_page>
						<last_page>337</last_page>
					</pages>
					<doi_data>
						<doi>10.21437/Odyssey.2022-46</doi>
						<resource>https://www.isca-archive.org/odyssey_2022/shim22_odyssey.html</resource>
					</doi_data>
				</conference_paper>
				<conference_paper publication_type="full_text">
					<contributors>
						<person_name sequence="first" contributor_role="author">
<given_name>Nikita</given_name>
<surname>Kuzmin</surname>
</person_name><person_name sequence="additional" contributor_role="author">
<given_name>Igor</given_name>
<surname>Fedorov</surname>
</person_name><person_name sequence="additional" contributor_role="author">
<given_name>Alexey</given_name>
<surname>Sholokhov</surname>
</person_name>
					</contributors>
					<titles><title>Magnitude-Aware Probabilistic Speaker Embeddings</title></titles>
					<publication_date media_type='online'>
						<month>6</month>
						<day>28</day>
						<year>2022</year>
					</publication_date>
					<pages>
						<first_page>1</first_page>
						<last_page>8</last_page>
					</pages>
					<doi_data>
						<doi>10.21437/Odyssey.2022-1</doi>
						<resource>https://www.isca-archive.org/odyssey_2022/kuzmin22_odyssey.html</resource>
					</doi_data>
				</conference_paper>
				<conference_paper publication_type="full_text">
					<contributors>
						<person_name sequence="first" contributor_role="author">
<given_name>Jincheng</given_name>
<surname>He</surname>
</person_name><person_name sequence="additional" contributor_role="author">
<given_name>Yuanyuan</given_name>
<surname>Bao</surname>
</person_name><person_name sequence="additional" contributor_role="author">
<given_name>Na</given_name>
<surname>Xu</surname>
</person_name><person_name sequence="additional" contributor_role="author">
<given_name>Hongfeng</given_name>
<surname>Li</surname>
</person_name><person_name sequence="additional" contributor_role="author">
<given_name>Shicong</given_name>
<surname>Li</surname>
</person_name><person_name sequence="additional" contributor_role="author">
<given_name>Linzhang</given_name>
<surname>Wang</surname>
</person_name><person_name sequence="additional" contributor_role="author">
<given_name>Fei</given_name>
<surname>Xiang</surname>
</person_name><person_name sequence="additional" contributor_role="author">
<given_name>Ming</given_name>
<surname>Li</surname>
</person_name>
					</contributors>
					<titles><title>Single-Channel Target Speaker Separation Using Joint Training with Target Speaker's Pitch Information</title></titles>
					<publication_date media_type='online'>
						<month>6</month>
						<day>28</day>
						<year>2022</year>
					</publication_date>
					<pages>
						<first_page>301</first_page>
						<last_page>305</last_page>
					</pages>
					<doi_data>
						<doi>10.21437/Odyssey.2022-42</doi>
						<resource>https://www.isca-archive.org/odyssey_2022/he22_odyssey.html</resource>
					</doi_data>
				</conference_paper>
				<conference_paper publication_type="full_text">
					<contributors>
						<person_name sequence="first" contributor_role="author">
<given_name>Haibin</given_name>
<surname>Wu</surname>
</person_name><person_name sequence="additional" contributor_role="author">
<given_name>Jiawen</given_name>
<surname>Kang</surname>
</person_name><person_name sequence="additional" contributor_role="author">
<given_name>Lingwei</given_name>
<surname>Meng</surname>
</person_name><person_name sequence="additional" contributor_role="author">
<given_name>Yang</given_name>
<surname>Zhang</surname>
</person_name><person_name sequence="additional" contributor_role="author">
<given_name>Xixin</given_name>
<surname>Wu</surname>
</person_name><person_name sequence="additional" contributor_role="author">
<given_name>Zhiyong</given_name>
<surname>Wu</surname>
</person_name><person_name sequence="additional" contributor_role="author">
<given_name>Hung-yi</given_name>
<surname>Lee</surname>
</person_name><person_name sequence="additional" contributor_role="author">
<given_name>Helen</given_name>
<surname>Meng</surname>
</person_name>
					</contributors>
					<titles><title>Tackling Spoofing-Aware Speaker Verification with Multi-Model Fusion</title></titles>
					<publication_date media_type='online'>
						<month>6</month>
						<day>28</day>
						<year>2022</year>
					</publication_date>
					<pages>
						<first_page>92</first_page>
						<last_page>99</last_page>
					</pages>
					<doi_data>
						<doi>10.21437/Odyssey.2022-13</doi>
						<resource>https://www.isca-archive.org/odyssey_2022/wu22_odyssey.html</resource>
					</doi_data>
				</conference_paper>
				<conference_paper publication_type="full_text">
					<contributors>
						<person_name sequence="first" contributor_role="author">
<given_name>Mohammad</given_name>
<surname>MohammadAmini</surname>
</person_name><person_name sequence="additional" contributor_role="author">
<given_name>Driss</given_name>
<surname>Matrouf</surname>
</person_name><person_name sequence="additional" contributor_role="author">
<given_name>Jean-François</given_name>
<surname>Bonastre</surname>
</person_name><person_name sequence="additional" contributor_role="author">
<given_name>Sandipana</given_name>
<surname>Dowerah</surname>
</person_name><person_name sequence="additional" contributor_role="author">
<given_name>Romain</given_name>
<surname>Serizel</surname>
</person_name><person_name sequence="additional" contributor_role="author">
<given_name>Denis</given_name>
<surname>Jouvet</surname>
</person_name>
					</contributors>
					<titles><title>Learning Noise Robust ResNet-Based Speaker Embedding for Speaker Recognition</title></titles>
					<publication_date media_type='online'>
						<month>6</month>
						<day>28</day>
						<year>2022</year>
					</publication_date>
					<pages>
						<first_page>41</first_page>
						<last_page>46</last_page>
					</pages>
					<doi_data>
						<doi>10.21437/Odyssey.2022-6</doi>
						<resource>https://www.isca-archive.org/odyssey_2022/mohammadamini22_odyssey.html</resource>
					</doi_data>
				</conference_paper>
				<conference_paper publication_type="full_text">
					<contributors>
						<person_name sequence="first" contributor_role="author">
<given_name>Zhuo</given_name>
<surname>Gong</surname>
</person_name><person_name sequence="additional" contributor_role="author">
<given_name>Daisuke</given_name>
<surname>Saito</surname>
</person_name><person_name sequence="additional" contributor_role="author">
<given_name>Longfei</given_name>
<surname>Yang</surname>
</person_name><person_name sequence="additional" contributor_role="author">
<given_name>Takahiro</given_name>
<surname>Shinozaki</surname>
</person_name><person_name sequence="additional" contributor_role="author">
<given_name>Sheng</given_name>
<surname>Li</surname>
</person_name><person_name sequence="additional" contributor_role="author">
<given_name>Hisashi</given_name>
<surname>Kawai</surname>
</person_name><person_name sequence="additional" contributor_role="author">
<given_name>Nobuaki</given_name>
<surname>Minematsu</surname>
</person_name>
					</contributors>
					<titles><title>Self-Adaptive Multilingual ASR Rescoring with Language Identification and Unified Language Model</title></titles>
					<publication_date media_type='online'>
						<month>6</month>
						<day>28</day>
						<year>2022</year>
					</publication_date>
					<pages>
						<first_page>415</first_page>
						<last_page>420</last_page>
					</pages>
					<doi_data>
						<doi>10.21437/Odyssey.2022-58</doi>
						<resource>https://www.isca-archive.org/odyssey_2022/gong22b_odyssey.html</resource>
					</doi_data>
				</conference_paper>
				<conference_paper publication_type="full_text">
					<contributors>
						<person_name sequence="first" contributor_role="author">
<given_name>Longting</given_name>
<surname>Xu</surname>
</person_name><person_name sequence="additional" contributor_role="author">
<given_name>Mianxin</given_name>
<surname>Tian</surname>
</person_name><person_name sequence="additional" contributor_role="author">
<given_name>Xing</given_name>
<surname>Guo</surname>
</person_name><person_name sequence="additional" contributor_role="author">
<given_name>Zhiyong</given_name>
<surname>Shan</surname>
</person_name><person_name sequence="additional" contributor_role="author">
<given_name>Jie</given_name>
<surname>Jia</surname>
</person_name><person_name sequence="additional" contributor_role="author">
<given_name>Yiyuan</given_name>
<surname>Peng</surname>
</person_name><person_name sequence="additional" contributor_role="author">
<given_name>Jichen</given_name>
<surname>Yang</surname>
</person_name><person_name sequence="additional" contributor_role="author">
<given_name>Rohan Kumar</given_name>
<surname>Das</surname>
</person_name>
					</contributors>
					<titles><title>A Novel Feature Based on Graph Signal Processing for Detection of Physical Access Attacks</title></titles>
					<publication_date media_type='online'>
						<month>6</month>
						<day>28</day>
						<year>2022</year>
					</publication_date>
					<pages>
						<first_page>107</first_page>
						<last_page>111</last_page>
					</pages>
					<doi_data>
						<doi>10.21437/Odyssey.2022-15</doi>
						<resource>https://www.isca-archive.org/odyssey_2022/xu22_odyssey.html</resource>
					</doi_data>
				</conference_paper>
				<conference_paper publication_type="full_text">
					<contributors>
						<person_name sequence="first" contributor_role="author">
<given_name>Chenguang</given_name>
<surname>Hu</surname>
</person_name><person_name sequence="additional" contributor_role="author">
<given_name>Qingran</given_name>
<surname>Zhan</surname>
</person_name><person_name sequence="additional" contributor_role="author">
<given_name>Miao</given_name>
<surname>Liu</surname>
</person_name><person_name sequence="additional" contributor_role="author">
<given_name>Xiang</given_name>
<surname>Xie</surname>
</person_name>
					</contributors>
					<titles><title>BIT Submission for the Conversational Speaker Diarization Challenge</title></titles>
					<publication_date media_type='online'>
						<month>6</month>
						<day>28</day>
						<year>2022</year>
					</publication_date>
					<pages>
						<first_page>148</first_page>
						<last_page>155</last_page>
					</pages>
					<doi_data>
						<doi>10.21437/Odyssey.2022-21</doi>
						<resource>https://www.isca-archive.org/odyssey_2022/hu22_odyssey.html</resource>
					</doi_data>
				</conference_paper>
				<conference_paper publication_type="full_text">
					<contributors>
						<person_name sequence="first" contributor_role="author">
<given_name>Anna</given_name>
<surname>Silnova</surname>
</person_name><person_name sequence="additional" contributor_role="author">
<given_name>Themos</given_name>
<surname>Stafylakis</surname>
</person_name><person_name sequence="additional" contributor_role="author">
<given_name>Ladislav</given_name>
<surname>Mošner</surname>
</person_name><person_name sequence="additional" contributor_role="author">
<given_name>Oldřich</given_name>
<surname>Plchot</surname>
</person_name><person_name sequence="additional" contributor_role="author">
<given_name>Johan</given_name>
<surname>Rohdin</surname>
</person_name><person_name sequence="additional" contributor_role="author">
<given_name>Pavel</given_name>
<surname>Matĕjka</surname>
</person_name><person_name sequence="additional" contributor_role="author">
<given_name>Lukáš</given_name>
<surname>Burget</surname>
</person_name><person_name sequence="additional" contributor_role="author">
<given_name>Ondřej</given_name>
<surname>Glembek</surname>
</person_name><person_name sequence="additional" contributor_role="author">
<given_name>Niko</given_name>
<surname>Brummer</surname>
</person_name>
					</contributors>
					<titles><title>Analyzing Speaker Verification Embedding Extractors and Back-Ends Under Language and Channel Mismatch</title></titles>
					<publication_date media_type='online'>
						<month>6</month>
						<day>28</day>
						<year>2022</year>
					</publication_date>
					<pages>
						<first_page>9</first_page>
						<last_page>16</last_page>
					</pages>
					<doi_data>
						<doi>10.21437/Odyssey.2022-2</doi>
						<resource>https://www.isca-archive.org/odyssey_2022/silnova22_odyssey.html</resource>
					</doi_data>
				</conference_paper>
				<conference_paper publication_type="full_text">
					<contributors>
						<person_name sequence="first" contributor_role="author">
<given_name>Anand</given_name>
<surname>Therattil</surname>
</person_name><person_name sequence="additional" contributor_role="author">
<given_name>Priyanka</given_name>
<surname>Gupta</surname>
</person_name><person_name sequence="additional" contributor_role="author">
<given_name>Piyushkumar K.</given_name>
<surname>Chodingala</surname>
</person_name><person_name sequence="additional" contributor_role="author">
<given_name>Hemant A.</given_name>
<surname>Patil</surname>
</person_name>
					</contributors>
					<titles><title>Teager Energy Based-Detection of One-point and Two-point Replay Attacks: Towards Cross-Database Generalization</title></titles>
					<publication_date media_type='online'>
						<month>6</month>
						<day>28</day>
						<year>2022</year>
					</publication_date>
					<pages>
						<first_page>47</first_page>
						<last_page>54</last_page>
					</pages>
					<doi_data>
						<doi>10.21437/Odyssey.2022-7</doi>
						<resource>https://www.isca-archive.org/odyssey_2022/therattil22_odyssey.html</resource>
					</doi_data>
				</conference_paper>
				<conference_paper publication_type="full_text">
					<contributors>
						<person_name sequence="first" contributor_role="author">
<given_name>Sandip</given_name>
<surname>Ghimire</surname>
</person_name><person_name sequence="additional" contributor_role="author">
<given_name>Tomi</given_name>
<surname>Kinnunen</surname>
</person_name><person_name sequence="additional" contributor_role="author">
<given_name>Rosa González</given_name>
<surname>Hautamäki</surname>
</person_name>
					</contributors>
					<titles><title>Gamified Speaker Comparison by Listening</title></titles>
					<publication_date media_type='online'>
						<month>6</month>
						<day>28</day>
						<year>2022</year>
					</publication_date>
					<pages>
						<first_page>421</first_page>
						<last_page>427</last_page>
					</pages>
					<doi_data>
						<doi>10.21437/Odyssey.2022-59</doi>
						<resource>https://www.isca-archive.org/odyssey_2022/ghimire22_odyssey.html</resource>
					</doi_data>
				</conference_paper>
				<conference_paper publication_type="full_text">
					<contributors>
						<person_name sequence="first" contributor_role="author">
<given_name>Haoran</given_name>
<surname>Sun</surname>
</person_name><person_name sequence="additional" contributor_role="author">
<given_name>Chen</given_name>
<surname>Chen</surname>
</person_name><person_name sequence="additional" contributor_role="author">
<given_name>Lantian</given_name>
<surname>Li</surname>
</person_name><person_name sequence="additional" contributor_role="author">
<given_name>Dong</given_name>
<surname>Wang</surname>
</person_name>
					</contributors>
					<titles><title>Cycleflow: Purify Information Factors by Cycle Loss</title></titles>
					<publication_date media_type='online'>
						<month>6</month>
						<day>28</day>
						<year>2022</year>
					</publication_date>
					<pages>
						<first_page>271</first_page>
						<last_page>278</last_page>
					</pages>
					<doi_data>
						<doi>10.21437/Odyssey.2022-38</doi>
						<resource>https://www.isca-archive.org/odyssey_2022/sun22_odyssey.html</resource>
					</doi_data>
				</conference_paper>
				<conference_paper publication_type="full_text">
					<contributors>
						<person_name sequence="first" contributor_role="author">
<given_name>You</given_name>
<surname>Zhang</surname>
</person_name><person_name sequence="additional" contributor_role="author">
<given_name>Ge</given_name>
<surname>Zhu</surname>
</person_name><person_name sequence="additional" contributor_role="author">
<given_name>Zhiyao</given_name>
<surname>Duan</surname>
</person_name>
					</contributors>
					<titles><title>A Probabilistic Fusion Framework for Spoofing Aware Speaker Verification</title></titles>
					<publication_date media_type='online'>
						<month>6</month>
						<day>28</day>
						<year>2022</year>
					</publication_date>
					<pages>
						<first_page>77</first_page>
						<last_page>84</last_page>
					</pages>
					<doi_data>
						<doi>10.21437/Odyssey.2022-11</doi>
						<resource>https://www.isca-archive.org/odyssey_2022/zhang22b_odyssey.html</resource>
					</doi_data>
				</conference_paper>
				<conference_paper publication_type="full_text">
					<contributors>
						<person_name sequence="first" contributor_role="author">
<given_name>Jahangir</given_name>
<surname>Alam</surname>
</person_name><person_name sequence="additional" contributor_role="author">
<given_name>Radek</given_name>
<surname>Beneš</surname>
</person_name><person_name sequence="additional" contributor_role="author">
<given_name>Marián</given_name>
<surname>Beszédeš</surname>
</person_name><person_name sequence="additional" contributor_role="author">
<given_name>Lukáš</given_name>
<surname>Burget</surname>
</person_name><person_name sequence="additional" contributor_role="author">
<given_name>Mohamed</given_name>
<surname>Dahmane</surname>
</person_name><person_name sequence="additional" contributor_role="author">
<given_name>Abderrahim</given_name>
<surname>Fathan</surname>
</person_name><person_name sequence="additional" contributor_role="author">
<given_name>Hamed</given_name>
<surname>Ghodrati</surname>
</person_name><person_name sequence="additional" contributor_role="author">
<given_name>Ondřej</given_name>
<surname>Glembek</surname>
</person_name><person_name sequence="additional" contributor_role="author">
<given_name>Woo Hyun</given_name>
<surname>Kang</surname>
</person_name><person_name sequence="additional" contributor_role="author">
<given_name>Pavel</given_name>
<surname>Matĕjka</surname>
</person_name><person_name sequence="additional" contributor_role="author">
<given_name>Ladislav</given_name>
<surname>Mošner</surname>
</person_name><person_name sequence="additional" contributor_role="author">
<given_name>Oldřich</given_name>
<surname>Plchot</surname>
</person_name><person_name sequence="additional" contributor_role="author">
<given_name>Johan</given_name>
<surname>Rohdin</surname>
</person_name><person_name sequence="additional" contributor_role="author">
<given_name>Anna</given_name>
<surname>Silnova</surname>
</person_name><person_name sequence="additional" contributor_role="author">
<given_name>Themos</given_name>
<surname>Stafylakis</surname>
</person_name>
					</contributors>
					<titles><title>Development of ABC Systems for the 2021 Edition of NIST Speaker Recognition Evaluation</title></titles>
					<publication_date media_type='online'>
						<month>6</month>
						<day>28</day>
						<year>2022</year>
					</publication_date>
					<pages>
						<first_page>346</first_page>
						<last_page>353</last_page>
					</pages>
					<doi_data>
						<doi>10.21437/Odyssey.2022-48</doi>
						<resource>https://www.isca-archive.org/odyssey_2022/alam22_odyssey.html</resource>
					</doi_data>
				</conference_paper>
				<conference_paper publication_type="full_text">
					<contributors>
						<person_name sequence="first" contributor_role="author">
<given_name>Yosef</given_name>
<surname>Solewicz</surname>
</person_name><person_name sequence="additional" contributor_role="author">
<given_name>Noa</given_name>
<surname>Cohen</surname>
</person_name><person_name sequence="additional" contributor_role="author">
<given_name>Johan</given_name>
<surname>Rohdin</surname>
</person_name><person_name sequence="additional" contributor_role="author">
<given_name>Srikanth</given_name>
<surname>Madikeri</surname>
</person_name><person_name sequence="additional" contributor_role="author">
<given_name>Jan ”Honza”</given_name>
<surname>Čercnocký</surname>
</person_name>
					</contributors>
					<titles><title>Speaker Recognition on Mono-Channel Telephony Recordings</title></titles>
					<publication_date media_type='online'>
						<month>6</month>
						<day>28</day>
						<year>2022</year>
					</publication_date>
					<pages>
						<first_page>193</first_page>
						<last_page>199</last_page>
					</pages>
					<doi_data>
						<doi>10.21437/Odyssey.2022-27</doi>
						<resource>https://www.isca-archive.org/odyssey_2022/solewicz22_odyssey.html</resource>
					</doi_data>
				</conference_paper>
				<conference_paper publication_type="full_text">
					<contributors>
						<person_name sequence="first" contributor_role="author">
<given_name>Haoxu</given_name>
<surname>Wang</surname>
</person_name><person_name sequence="additional" contributor_role="author">
<given_name>Yan</given_name>
<surname>Jia</surname>
</person_name><person_name sequence="additional" contributor_role="author">
<given_name>Zeqing</given_name>
<surname>Zhao</surname>
</person_name><person_name sequence="additional" contributor_role="author">
<given_name>Xuyang</given_name>
<surname>Wang</surname>
</person_name><person_name sequence="additional" contributor_role="author">
<given_name>Junjie</given_name>
<surname>Wang</surname>
</person_name><person_name sequence="additional" contributor_role="author">
<given_name>Ming</given_name>
<surname>Li</surname>
</person_name>
					</contributors>
					<titles><title>Generating TTS Based Adversarial Samples for Training Wake-Up Word Detection Systems Against Confusing Words</title></titles>
					<publication_date media_type='online'>
						<month>6</month>
						<day>28</day>
						<year>2022</year>
					</publication_date>
					<pages>
						<first_page>402</first_page>
						<last_page>406</last_page>
					</pages>
					<doi_data>
						<doi>10.21437/Odyssey.2022-56</doi>
						<resource>https://www.isca-archive.org/odyssey_2022/wang22c_odyssey.html</resource>
					</doi_data>
				</conference_paper>
				<conference_paper publication_type="full_text">
					<contributors>
						<person_name sequence="first" contributor_role="author">
<given_name>Jahangir</given_name>
<surname>Alam</surname>
</person_name><person_name sequence="additional" contributor_role="author">
<given_name>Woo Hyun</given_name>
<surname>Kang</surname>
</person_name><person_name sequence="additional" contributor_role="author">
<given_name>Abderrahim</given_name>
<surname>Fathan</surname>
</person_name>
					</contributors>
					<titles><title>Hybrid Neural Network-Based Deep Embedding Extractors for Text-Independent Speaker Verification</title></titles>
					<publication_date media_type='online'>
						<month>6</month>
						<day>28</day>
						<year>2022</year>
					</publication_date>
					<pages>
						<first_page>33</first_page>
						<last_page>40</last_page>
					</pages>
					<doi_data>
						<doi>10.21437/Odyssey.2022-5</doi>
						<resource>https://www.isca-archive.org/odyssey_2022/alam22b_odyssey.html</resource>
					</doi_data>
				</conference_paper>
				<conference_paper publication_type="full_text">
					<contributors>
						<person_name sequence="first" contributor_role="author">
<given_name>Jintao</given_name>
<surname>Kang</surname>
</person_name><person_name sequence="additional" contributor_role="author">
<given_name>Aijun</given_name>
<surname>Li</surname>
</person_name><person_name sequence="additional" contributor_role="author">
<given_name>Jingyang</given_name>
<surname>Li</surname>
</person_name>
					</contributors>
					<titles><title>Formant Dynamics of Chinese Compound Vowels with Implications for Forensic Speaker Identification</title></titles>
					<publication_date media_type='online'>
						<month>6</month>
						<day>28</day>
						<year>2022</year>
					</publication_date>
					<pages>
						<first_page>396</first_page>
						<last_page>401</last_page>
					</pages>
					<doi_data>
						<doi>10.21437/Odyssey.2022-55</doi>
						<resource>https://www.isca-archive.org/odyssey_2022/kang22c_odyssey.html</resource>
					</doi_data>
				</conference_paper>
				<conference_paper publication_type="full_text">
					<contributors>
						<person_name sequence="first" contributor_role="author">
<given_name>YingWei</given_name>
<surname>Tan</surname>
</person_name><person_name sequence="additional" contributor_role="author">
<given_name>XueFeng</given_name>
<surname>Ding</surname>
</person_name>
					</contributors>
					<titles><title>The Volkswagen-Mobvoi System for CN-Celeb Speaker Recognition Challenge 2022</title></titles>
					<publication_date media_type='online'>
						<month>6</month>
						<day>28</day>
						<year>2022</year>
					</publication_date>
					<pages>
						<first_page>362</first_page>
						<last_page>367</last_page>
					</pages>
					<doi_data>
						<doi>10.21437/Odyssey.2022-50</doi>
						<resource>https://www.isca-archive.org/odyssey_2022/tan22_odyssey.html</resource>
					</doi_data>
				</conference_paper>
				<conference_paper publication_type="full_text">
					<contributors>
						<person_name sequence="first" contributor_role="author">
<given_name>Woo Hyun</given_name>
<surname>Kang</surname>
</person_name><person_name sequence="additional" contributor_role="author">
<given_name>Jahangir</given_name>
<surname>Alam</surname>
</person_name>
					</contributors>
					<titles><title>Investigation on Deep Speaker Embedding Extraction Methods for Multi-Genre Speaker Verification</title></titles>
					<publication_date media_type='online'>
						<month>6</month>
						<day>28</day>
						<year>2022</year>
					</publication_date>
					<pages>
						<first_page>376</first_page>
						<last_page>383</last_page>
					</pages>
					<doi_data>
						<doi>10.21437/Odyssey.2022-52</doi>
						<resource>https://www.isca-archive.org/odyssey_2022/kang22d_odyssey.html</resource>
					</doi_data>
				</conference_paper>
				<conference_paper publication_type="full_text">
					<contributors>
						<person_name sequence="first" contributor_role="author">
<given_name>Jialin</given_name>
<surname>Zhang</surname>
</person_name><person_name sequence="additional" contributor_role="author">
<given_name>Qinghua</given_name>
<surname>Ren</surname>
</person_name><person_name sequence="additional" contributor_role="author">
<given_name>Youcai</given_name>
<surname>Qin</surname>
</person_name><person_name sequence="additional" contributor_role="author">
<given_name>Zikai</given_name>
<surname>Wan</surname>
</person_name><person_name sequence="additional" contributor_role="author">
<given_name>Qirong</given_name>
<surname>Mao</surname>
</person_name>
					</contributors>
					<titles><title>Cross-Scene Speaker Verification Based on Dynamic Convolution for the CNSRC 2022 Challenge</title></titles>
					<publication_date media_type='online'>
						<month>6</month>
						<day>28</day>
						<year>2022</year>
					</publication_date>
					<pages>
						<first_page>368</first_page>
						<last_page>375</last_page>
					</pages>
					<doi_data>
						<doi>10.21437/Odyssey.2022-51</doi>
						<resource>https://www.isca-archive.org/odyssey_2022/zhang22c_odyssey.html</resource>
					</doi_data>
				</conference_paper>
				<conference_paper publication_type="full_text">
					<contributors>
						<person_name sequence="first" contributor_role="author">
<given_name>Xinmei</given_name>
<surname>Su</surname>
</person_name><person_name sequence="additional" contributor_role="author">
<given_name>Qingran</given_name>
<surname>Zhan</surname>
</person_name><person_name sequence="additional" contributor_role="author">
<given_name>Chenguang</given_name>
<surname>Hu</surname>
</person_name><person_name sequence="additional" contributor_role="author">
<given_name>Xiang</given_name>
<surname>Xie</surname>
</person_name>
					</contributors>
					<titles><title>Combination of Multiple Embeddings for Speaker Retrieval</title></titles>
					<publication_date media_type='online'>
						<month>6</month>
						<day>28</day>
						<year>2022</year>
					</publication_date>
					<pages>
						<first_page>384</first_page>
						<last_page>389</last_page>
					</pages>
					<doi_data>
						<doi>10.21437/Odyssey.2022-53</doi>
						<resource>https://www.isca-archive.org/odyssey_2022/su22_odyssey.html</resource>
					</doi_data>
				</conference_paper>
		</conference>
	</body>
</doi_batch>